[
  {
    "workflow_id": "03b02bfe-a84f-4fbe-88f8-a65d7cdca90e",
    "true_class": "SOW kickoff and order form creation",
    "predicted_class": "SOW iteration",
    "correct": false
  },
  {
    "workflow_id": "08a64828-b50c-4820-b374-fb17ab5da7eb",
    "true_class": "Legal finalization and SOW execution",
    "predicted_class": "Legal finalization and SOW execution",
    "correct": true
  },
  {
    "workflow_id": "0b874e79-5cd0-4fb7-ac1a-459a6b90e415",
    "true_class": "SOW iteration",
    "predicted_class": "Legal finalization and SOW execution",
    "correct": false
  },
  {
    "workflow_id": "0f5150bb-dcfe-4893-8063-dbade668b5ce",
    "true_class": "Contract kickoff",
    "predicted_class": "SOW iteration",
    "correct": false
  },
  {
    "workflow_id": "0f83eaa6-6bc7-44b4-aabb-a923737aa4a0",
    "true_class": "Contract kickoff",
    "predicted_class": "Legal finalization and SOW execution",
    "correct": false
  },
  {
    "workflow_id": "1188383f-b539-4c43-a5b0-85dad6d72400",
    "true_class": "SOW kickoff and order form creation",
    "predicted_class": "SOW iteration",
    "correct": false
  },
  {
    "workflow_id": "170ffdc5-bf90-4abe-a096-9996678e2587",
    "true_class": "Legal finalization and SOW execution",
    "predicted_class": "SOW kickoff and order form creation",
    "correct": false
  },
  {
    "workflow_id": "1b94e1f9-a5f2-48b6-94ea-d31cbcaba11d",
    "true_class": "Contract kickoff",
    "predicted_class": "Legal finalization and SOW execution",
    "correct": false
  },
  {
    "workflow_id": "1bc626be-bb3f-4cc2-b6e6-807404585851",
    "true_class": "Legal finalization and SOW execution",
    "predicted_class": "Legal finalization and SOW execution",
    "correct": true
  },
  {
    "workflow_id": "204b52b1-51bf-4153-b7a0-358d403387ac",
    "true_class": "Legal finalization and SOW execution",
    "predicted_class": "Legal finalization and SOW execution",
    "correct": true
  },
  {
    "workflow_id": "21539685-af57-46e9-be21-95d8b9da585c",
    "true_class": "SOW iteration",
    "predicted_class": "SOW iteration",
    "correct": true
  },
  {
    "workflow_id": "226b1103-c8fa-4c90-a255-c38f6d7a9a3a",
    "true_class": "SOW kickoff and order form creation",
    "predicted_class": "SOW kickoff and order form creation",
    "correct": true
  },
  {
    "workflow_id": "2765cbb5-36f3-41e0-9830-a08df0417086",
    "true_class": "Legal finalization and SOW execution",
    "predicted_class": "Legal finalization and SOW execution",
    "correct": true
  },
  {
    "workflow_id": "2a6b51f6-54b6-43f5-a627-8b33a6a71cec",
    "true_class": "SOW kickoff and order form creation",
    "predicted_class": "SOW iteration",
    "correct": false
  },
  {
    "workflow_id": "2c2e8402-1974-4bf9-bf45-a0b8a9d9edeb",
    "true_class": "Legal finalization and MSA execution",
    "predicted_class": "Legal finalization and SOW execution",
    "correct": false
  },
  {
    "workflow_id": "34f440dd-d5ed-47f0-9231-31a401a54bc3",
    "true_class": "Contract kickoff",
    "predicted_class": "SOW kickoff and order form creation",
    "correct": false
  },
  {
    "workflow_id": "38c86815-9387-4e97-a9be-c39ec042b23d",
    "true_class": "SOW iteration",
    "predicted_class": "SOW iteration",
    "correct": true
  },
  {
    "workflow_id": "39f43cc2-44d1-49a0-aeed-468d2657581e",
    "true_class": "Legal finalization and SOW execution",
    "predicted_class": "Legal finalization and SOW execution",
    "correct": true
  },
  {
    "workflow_id": "3a95679b-b767-438e-813d-3fddd901c1f9",
    "true_class": "Legal finalization and SOW execution",
    "predicted_class": "Legal finalization and MSA execution",
    "correct": false
  },
  {
    "workflow_id": "3b1e799a-7671-47a4-b099-94e2becda241",
    "true_class": "Legal finalization and SOW execution",
    "predicted_class": "Legal finalization and SOW execution",
    "correct": true
  },
  {
    "workflow_id": "3d65899b-51c4-480d-8629-0c05af27bcd3",
    "true_class": "SOW iteration",
    "predicted_class": "Legal finalization and MSA execution",
    "correct": false
  },
  {
    "workflow_id": "40b0bdc5-8cb6-4cb1-bc70-205b348f0781",
    "true_class": "Legal finalization and SOW execution",
    "predicted_class": "Legal finalization and SOW execution",
    "correct": true
  },
  {
    "workflow_id": "41b1147e-4cc7-45aa-ad3f-55e348094a0e",
    "true_class": "SOW kickoff and order form creation",
    "predicted_class": "Legal finalization and SOW execution",
    "correct": false
  },
  {
    "workflow_id": "4257f216-38d8-4153-9622-827ff5f0bc2e",
    "true_class": "SOW kickoff and order form creation",
    "predicted_class": "Legal finalization and SOW execution",
    "correct": false
  },
  {
    "workflow_id": "439f8ae3-f5e1-45c9-9d55-16716bf8de17",
    "true_class": "Legal finalization and SOW execution",
    "predicted_class": "SOW kickoff and order form creation",
    "correct": false
  },
  {
    "workflow_id": "4891f312-1abe-42ec-b262-f68555225bd7",
    "true_class": "Legal finalization and SOW execution",
    "predicted_class": "SOW kickoff and order form creation",
    "correct": false
  },
  {
    "workflow_id": "4944b434-fe5e-41ec-af9c-d18644bd6acb",
    "true_class": "Legal finalization and SOW execution",
    "predicted_class": "Legal finalization and SOW execution",
    "correct": true
  },
  {
    "workflow_id": "4b52cf5b-4b67-4e9d-a22d-badbf2f6d0c6",
    "true_class": "Contract kickoff",
    "predicted_class": "SOW kickoff and order form creation",
    "correct": false
  },
  {
    "workflow_id": "4b7732fa-7ad9-4e74-8cdc-164829e84858",
    "true_class": "Contract kickoff",
    "predicted_class": "SOW kickoff and order form creation",
    "correct": false
  },
  {
    "workflow_id": "4d270271-be17-438a-8d03-90062bca88cb",
    "true_class": "Contract kickoff",
    "predicted_class": "SOW iteration",
    "correct": false
  },
  {
    "workflow_id": "4dc55b3d-9538-47b8-8e46-c931ac6dbc0b",
    "true_class": "SOW iteration",
    "predicted_class": "Legal finalization and MSA execution",
    "correct": false
  },
  {
    "workflow_id": "4ddd2277-a8ff-4da3-987b-334d7b3b188b",
    "true_class": "Legal finalization and SOW execution",
    "predicted_class": "Legal finalization and SOW execution",
    "correct": true
  },
  {
    "workflow_id": "4e410e22-301e-444b-8331-5af25e442278",
    "true_class": "Legal finalization and SOW execution",
    "predicted_class": "Legal finalization and SOW execution",
    "correct": true
  },
  {
    "workflow_id": "522b5a34-f802-4fa3-b970-53c1fb1e1642",
    "true_class": "Legal finalization and SOW execution",
    "predicted_class": "Legal finalization and SOW execution",
    "correct": true
  },
  {
    "workflow_id": "56228ef3-a9fc-4b3d-b5e7-2a79aa947bd2",
    "true_class": "Legal finalization and SOW execution",
    "predicted_class": "Legal finalization and SOW execution",
    "correct": true
  },
  {
    "workflow_id": "57b557eb-6125-4faa-be66-a541ca459012",
    "true_class": "Legal finalization and SOW execution",
    "predicted_class": "Legal finalization and SOW execution",
    "correct": true
  },
  {
    "workflow_id": "5c83f0b2-67b4-4206-95f0-9b74b9431827",
    "true_class": "Legal finalization and SOW execution",
    "predicted_class": "Legal finalization and SOW execution",
    "correct": true
  },
  {
    "workflow_id": "5fbe6548-387d-442e-b294-46eb30d5d874",
    "true_class": "Legal finalization and SOW execution",
    "predicted_class": "SOW kickoff and order form creation",
    "correct": false
  },
  {
    "workflow_id": "5fe79f12-0919-49d4-8630-4ab6396bd08e",
    "true_class": "Legal finalization and SOW execution",
    "predicted_class": "Legal finalization and SOW execution",
    "correct": true
  },
  {
    "workflow_id": "6a8fb8db-8770-4000-b667-478175308901",
    "true_class": "SOW iteration",
    "predicted_class": "Legal finalization and SOW execution",
    "correct": false
  },
  {
    "workflow_id": "70ab5995-e614-44e4-b70e-0a3bd5230a26",
    "true_class": "SOW kickoff and order form creation",
    "predicted_class": "Legal finalization and SOW execution",
    "correct": false
  },
  {
    "workflow_id": "725bd8e8-ff6d-4375-ab94-3e94e10c129c",
    "true_class": "Legal finalization and SOW execution",
    "predicted_class": "Legal finalization and SOW execution",
    "correct": true
  },
  {
    "workflow_id": "73f04c9e-b771-4f52-b864-7cf7aa3999ca",
    "true_class": "Legal finalization and SOW execution",
    "predicted_class": "SOW kickoff and order form creation",
    "correct": false
  },
  {
    "workflow_id": "755a112c-8217-4fc4-a659-10c737f79c2f",
    "true_class": "SOW kickoff and order form creation",
    "predicted_class": "SOW kickoff and order form creation",
    "correct": true
  },
  {
    "workflow_id": "758b348e-7624-458f-9d02-f175a22afdc2",
    "true_class": "Legal finalization and SOW execution",
    "predicted_class": "Legal finalization and SOW execution",
    "correct": true
  },
  {
    "workflow_id": "75f06b95-2c20-463a-b570-d8528d0aa768",
    "true_class": "SOW iteration",
    "predicted_class": "Legal finalization and SOW execution",
    "correct": false
  },
  {
    "workflow_id": "76fff281-fc5a-4cf9-aecc-1b88991ad8a0",
    "true_class": "SOW iteration",
    "predicted_class": "SOW kickoff and order form creation",
    "correct": false
  },
  {
    "workflow_id": "7861210f-3020-4d65-a837-e8434642399d",
    "true_class": "Legal finalization and SOW execution",
    "predicted_class": "Legal finalization and SOW execution",
    "correct": true
  },
  {
    "workflow_id": "78ea02ce-e684-4980-a60f-bfa7db922aa8",
    "true_class": "SOW iteration",
    "predicted_class": "SOW iteration",
    "correct": true
  },
  {
    "workflow_id": "7913aa9f-265a-4b46-9c25-34c9bdfa5f3a",
    "true_class": "SOW iteration",
    "predicted_class": "SOW kickoff and order form creation",
    "correct": false
  },
  {
    "workflow_id": "7baac1bd-0ae0-4bf9-847d-c80e62798274",
    "true_class": "First pass contract review",
    "predicted_class": "Legal finalization and MSA execution",
    "correct": false
  },
  {
    "workflow_id": "7fd3d9e7-46c1-4749-ac96-567ee3f9d716",
    "true_class": "SOW iteration",
    "predicted_class": "SOW kickoff and order form creation",
    "correct": false
  },
  {
    "workflow_id": "81594ffe-75fd-433e-864e-bc2f4e34e436",
    "true_class": "Contract kickoff",
    "predicted_class": "Legal finalization and SOW execution",
    "correct": false
  },
  {
    "workflow_id": "8374c72b-4dfa-414e-8585-016a4526c2d6",
    "true_class": "Contract kickoff",
    "predicted_class": "SOW kickoff and order form creation",
    "correct": false
  },
  {
    "workflow_id": "88e44bcc-518a-4859-95e0-62e7ed18e4eb",
    "true_class": "Legal finalization and SOW execution",
    "predicted_class": "Legal finalization and SOW execution",
    "correct": true
  },
  {
    "workflow_id": "8c8045e8-ca31-40be-a5dc-65c7004846e3",
    "true_class": "Contract kickoff",
    "predicted_class": "SOW iteration",
    "correct": false
  },
  {
    "workflow_id": "8ca884fb-5b90-4d00-a7c8-67eceac10a84",
    "true_class": "SOW iteration",
    "predicted_class": "SOW iteration",
    "correct": true
  },
  {
    "workflow_id": "8e7e8895-929b-4886-a8c3-63bc93483b2c",
    "true_class": "SOW iteration",
    "predicted_class": "SOW iteration",
    "correct": true
  },
  {
    "workflow_id": "8f5285fd-5f94-48c4-b916-d4d75052d325",
    "true_class": "Legal finalization and SOW execution",
    "predicted_class": "Legal finalization and SOW execution",
    "correct": true
  },
  {
    "workflow_id": "8fbbfa58-1e0b-49df-a7ca-8ee58f510158",
    "true_class": "Legal finalization and SOW execution",
    "predicted_class": "Legal finalization and SOW execution",
    "correct": true
  },
  {
    "workflow_id": "97793e71-266b-4c72-8421-56d005ce7988",
    "true_class": "SOW iteration",
    "predicted_class": "Legal finalization and SOW execution",
    "correct": false
  },
  {
    "workflow_id": "97d1525f-c42f-481b-b1bc-52bb7c121630",
    "true_class": "SOW iteration",
    "predicted_class": "Legal finalization and SOW execution",
    "correct": false
  },
  {
    "workflow_id": "9e55ecd8-06b0-485e-b998-bbc10aaf9d76",
    "true_class": "SOW kickoff and order form creation",
    "predicted_class": "SOW iteration",
    "correct": false
  },
  {
    "workflow_id": "9e5e296b-db7e-4c4e-a263-9f8fb22d9095",
    "true_class": "SOW iteration",
    "predicted_class": "Legal finalization and MSA execution",
    "correct": false
  },
  {
    "workflow_id": "a197f9b9-cab5-44af-bdfb-8ea0525f5478",
    "true_class": "SOW kickoff and order form creation",
    "predicted_class": "SOW iteration",
    "correct": false
  },
  {
    "workflow_id": "a69d5a78-78bb-46cb-957e-8e3b9860505d",
    "true_class": "Contract kickoff",
    "predicted_class": "Legal finalization and SOW execution",
    "correct": false
  },
  {
    "workflow_id": "a8338369-ab56-4a13-861f-703783b19381",
    "true_class": "Contract kickoff",
    "predicted_class": "SOW kickoff and order form creation",
    "correct": false
  },
  {
    "workflow_id": "abefac46-a1a8-4d51-9191-638acf24e886",
    "true_class": "MSA contract iteration",
    "predicted_class": "SOW iteration",
    "correct": false
  },
  {
    "workflow_id": "ac700af8-31f0-46e6-89cd-428403e61337",
    "true_class": "Contract kickoff",
    "predicted_class": "SOW iteration",
    "correct": false
  },
  {
    "workflow_id": "ad9977e1-3778-4733-9136-9e4a7c489341",
    "true_class": "Contract kickoff",
    "predicted_class": "SOW kickoff and order form creation",
    "correct": false
  },
  {
    "workflow_id": "aee28b66-1f75-4376-922e-2b9ce6215d2c",
    "true_class": "SOW iteration",
    "predicted_class": "SOW iteration",
    "correct": true
  },
  {
    "workflow_id": "affae27c-a8fa-4194-8ecf-44ef14700b56",
    "true_class": "SOW kickoff and order form creation",
    "predicted_class": "First pass contract review",
    "correct": false
  },
  {
    "workflow_id": "b22480f6-5fe6-4eb5-985b-d30232d94421",
    "true_class": "Legal finalization and SOW execution",
    "predicted_class": "Legal finalization and SOW execution",
    "correct": true
  },
  {
    "workflow_id": "b333e6f7-026b-4d57-80d0-af2c9dfad08a",
    "true_class": "SOW kickoff and order form creation",
    "predicted_class": "Legal finalization and SOW execution",
    "correct": false
  },
  {
    "workflow_id": "b3638008-db66-453c-bb75-fa111134f536",
    "true_class": "SOW kickoff and order form creation",
    "predicted_class": "SOW kickoff and order form creation",
    "correct": true
  },
  {
    "workflow_id": "b519a434-3c50-4a66-8889-2a7c7663d48c",
    "true_class": "Contract kickoff",
    "predicted_class": "SOW iteration",
    "correct": false
  },
  {
    "workflow_id": "ba7e17da-42d7-4037-9ca2-0e1479871091",
    "true_class": "SOW kickoff and order form creation",
    "predicted_class": "SOW iteration",
    "correct": false
  },
  {
    "workflow_id": "baef41e4-ab9b-42e1-9d82-56c5229a5c2f",
    "true_class": "Legal finalization and SOW execution",
    "predicted_class": "SOW kickoff and order form creation",
    "correct": false
  },
  {
    "workflow_id": "beed35a0-6c96-4b56-9811-ef9551bd5949",
    "true_class": "SOW kickoff and order form creation",
    "predicted_class": "SOW iteration",
    "correct": false
  },
  {
    "workflow_id": "bff777c4-6a39-43a8-a1f0-a77d7e99761e",
    "true_class": "SOW kickoff and order form creation",
    "predicted_class": "SOW kickoff and order form creation",
    "correct": true
  },
  {
    "workflow_id": "c259071d-3936-4ef1-8179-08a29ec1ce21",
    "true_class": "Contract kickoff",
    "predicted_class": "Legal finalization and SOW execution",
    "correct": false
  },
  {
    "workflow_id": "c4c7220c-1b48-4fcf-92a7-72001d96b67f",
    "true_class": "Legal finalization and SOW execution",
    "predicted_class": "Legal finalization and SOW execution",
    "correct": true
  },
  {
    "workflow_id": "c51f1f69-7789-4f41-919c-cc8c82d5a42c",
    "true_class": "SOW iteration",
    "predicted_class": "SOW kickoff and order form creation",
    "correct": false
  },
  {
    "workflow_id": "c5ec963b-be71-491e-b32d-bca422ac980a",
    "true_class": "Legal finalization and SOW execution",
    "predicted_class": "Legal finalization and SOW execution",
    "correct": true
  },
  {
    "workflow_id": "c8e15330-ef8a-419b-8257-196d011a21c6",
    "true_class": "Contract kickoff",
    "predicted_class": "Legal finalization and SOW execution",
    "correct": false
  },
  {
    "workflow_id": "cb7b70df-c8db-414d-ae51-14cda211fffc",
    "true_class": "Contract kickoff",
    "predicted_class": "Legal finalization and SOW execution",
    "correct": false
  },
  {
    "workflow_id": "cca84a12-c9b4-4f0a-b06a-19f5f2120bc8",
    "true_class": "Contract kickoff",
    "predicted_class": "Legal finalization and MSA execution",
    "correct": false
  },
  {
    "workflow_id": "cfb092b2-2fce-4fa6-93f6-f4e7ff4cfdbc",
    "true_class": "SOW kickoff and order form creation",
    "predicted_class": "SOW iteration",
    "correct": false
  },
  {
    "workflow_id": "d1209245-30f4-4a93-bf62-66c4697f2a66",
    "true_class": "Legal finalization and SOW execution",
    "predicted_class": "Legal finalization and SOW execution",
    "correct": true
  },
  {
    "workflow_id": "d2b5995c-d52a-47a9-ab6f-90746c67f5a6",
    "true_class": "SOW kickoff and order form creation",
    "predicted_class": "SOW iteration",
    "correct": false
  },
  {
    "workflow_id": "dc794a43-11f6-46db-b05a-b394ccdd9b89",
    "true_class": "SOW kickoff and order form creation",
    "predicted_class": "SOW kickoff and order form creation",
    "correct": true
  },
  {
    "workflow_id": "df27ef2e-503a-4ac3-bb23-fffce6f2ab15",
    "true_class": "Contract kickoff",
    "predicted_class": "SOW kickoff and order form creation",
    "correct": false
  },
  {
    "workflow_id": "e2c78243-f1dd-42fa-8a6a-4ba3eb1cd856",
    "true_class": "Legal finalization and SOW execution",
    "predicted_class": "Legal finalization and SOW execution",
    "correct": true
  },
  {
    "workflow_id": "e9d06d5f-e643-4e7f-b7e8-0cca21551d64",
    "true_class": "Legal finalization and SOW execution",
    "predicted_class": "Legal finalization and SOW execution",
    "correct": true
  },
  {
    "workflow_id": "ead512b7-d587-4b93-8eb3-6af1a88fc822",
    "true_class": "Legal finalization and SOW execution",
    "predicted_class": "Legal finalization and MSA execution",
    "correct": false
  },
  {
    "workflow_id": "eb5d52ec-afdf-4178-a770-6a5e1ea96deb",
    "true_class": "SOW iteration",
    "predicted_class": "SOW kickoff and order form creation",
    "correct": false
  },
  {
    "workflow_id": "edceb8c4-7957-4690-bb99-d73e2611ad2e",
    "true_class": "SOW kickoff and order form creation",
    "predicted_class": "SOW kickoff and order form creation",
    "correct": true
  },
  {
    "workflow_id": "eeab05ae-e9d6-4699-af35-5e7d992d5868",
    "true_class": "Contract kickoff",
    "predicted_class": "Legal finalization and SOW execution",
    "correct": false
  },
  {
    "workflow_id": "f719e918-a14c-4724-ab04-e39da1357b5d",
    "true_class": "SOW iteration",
    "predicted_class": "SOW iteration",
    "correct": true
  },
  {
    "workflow_id": "f81b6d16-801b-47de-9c38-a5d2ca3dbe96",
    "true_class": "Legal finalization and SOW execution",
    "predicted_class": "Legal finalization and SOW execution",
    "correct": true
  },
  {
    "workflow_id": "fa01a7dd-ee89-4548-b034-185b54449a5c",
    "true_class": "Contract kickoff",
    "predicted_class": "SOW kickoff and order form creation",
    "correct": false
  },
  {
    "workflow_id": "ff89c80f-98a8-48c4-8d9c-15ee08a8d399",
    "true_class": "Legal finalization and SOW execution",
    "predicted_class": "Legal finalization and SOW execution",
    "correct": true
  }
]